pywf_internal_proprietary/__init__.py
pywf_internal_proprietary/_version.py
pywf_internal_proprietary/_version.tpl
pywf_internal_proprietary/api.py
pywf_internal_proprietary/define.py
pywf_internal_proprietary/define_01_paths.py
pywf_internal_proprietary/define_02_venv.py
pywf_internal_proprietary/define_03_deps.py
pywf_internal_proprietary/define_04_tests.py
pywf_internal_proprietary/define_05_docs.py
pywf_internal_proprietary/define_06_build.py
pywf_internal_proprietary/define_07_publish.py
pywf_internal_proprietary/define_08_saas.py
pywf_internal_proprietary/define_09_aws.py
pywf_internal_proprietary/define_10_cloudflare.py
pywf_internal_proprietary/helpers.py
pywf_internal_proprietary/logger.py
pywf_internal_proprietary/paths.py
pywf_internal_proprietary/runtime.py
pywf_internal_proprietary/vendor/__init__.py
pywf_internal_proprietary/vendor/better_pathlib.py
pywf_internal_proprietary/vendor/build_dist.py
pywf_internal_proprietary/vendor/emoji.py
pywf_internal_proprietary/vendor/home_secret.py
pywf_internal_proprietary/vendor/jsonutils.py
pywf_internal_proprietary/vendor/os_platform.py
pywf_internal_proprietary/vendor/pytest_cov_helper.py
pywf_internal_proprietary/vendor/vislog/__init__.py
pywf_internal_proprietary/vendor/vislog/_version.py
pywf_internal_proprietary/vendor/vislog/impl.py
pywf_internal_proprietary-0.1.12.dist-info/AUTHORS.rst
pywf_internal_proprietary-0.1.12.dist-info/LICENSE.txt
pywf_internal_proprietary-0.1.12.dist-info/METADATA
pywf_internal_proprietary-0.1.12.dist-info/WHEEL
pywf_internal_proprietary-0.1.12.dist-info/RECORD
